catmail/__init__.py
catmail/config.py
catmail/mailer.py
catmail/reader.py
catmail/scanner.py
catmail/util.py
catmail-0.1.9.1.dist-info/LICENSE
catmail-0.1.9.1.dist-info/METADATA
catmail-0.1.9.1.dist-info/WHEEL
catmail-0.1.9.1.dist-info/top_level.txt
catmail-0.1.9.1.dist-info/RECORD
