Metadata-Version: 2.1
Name: catmail
Version: 0.1.9.1
Summary: email tools for cats
Author: Mario Balibrera
Author-email: mario.balibrera@gmail.com
License: MIT License
Classifier: Development Status :: 3 - Alpha
Classifier: Environment :: Console
Classifier: Intended Audience :: Developers
Classifier: License :: OSI Approved :: MIT License
Classifier: Operating System :: OS Independent
Classifier: Programming Language :: Python
Classifier: Topic :: Software Development :: Libraries :: Python Modules
License-File: LICENSE
Requires-Dist: fyg >=0.1.6
Requires-Dist: rel >=0.4.9.20
Requires-Dist: yagmail >=0.6.161
